vsutillib/misc/__init__.py
vsutillib/misc/cipher.py
vsutillib/misc/decorators.py
vsutillib/misc/regexutils.py
vsutillib/misc/strFormatTimeDelta.py
vsutillib/misc/classes/XLate.py
vsutillib/misc/classes/__init__.py
vsutillib_misc-1.6.0.dist-info/AUTHORS
vsutillib_misc-1.6.0.dist-info/LICENSE.txt
vsutillib_misc-1.6.0.dist-info/METADATA
vsutillib_misc-1.6.0.dist-info/WHEEL
vsutillib_misc-1.6.0.dist-info/top_level.txt
vsutillib_misc-1.6.0.dist-info/RECORD
